setup.py
hpsunnyday/__init__.py
hpsunnyday/hpsunnyday.py
hpsunnyday.egg-info/PKG-INFO
hpsunnyday.egg-info/SOURCES.txt
hpsunnyday.egg-info/dependency_links.txt
hpsunnyday.egg-info/requires.txt
hpsunnyday.egg-info/top_level.txt